odoo/addons/stock_warehouse_relationship/README.rst
odoo/addons/stock_warehouse_relationship/__init__.py
odoo/addons/stock_warehouse_relationship/__manifest__.py
odoo/addons/stock_warehouse_relationship/i18n/fr.po
odoo/addons/stock_warehouse_relationship/i18n/it.po
odoo/addons/stock_warehouse_relationship/i18n/stock_warehouse_relationship.pot
odoo/addons/stock_warehouse_relationship/models/__init__.py
odoo/addons/stock_warehouse_relationship/models/stock_move.py
odoo/addons/stock_warehouse_relationship/models/stock_move_line.py
odoo/addons/stock_warehouse_relationship/models/stock_picking.py
odoo/addons/stock_warehouse_relationship/models/stock_quant.py
odoo/addons/stock_warehouse_relationship/models/stock_quant_package.py
odoo/addons/stock_warehouse_relationship/readme/CONTRIBUTORS.rst
odoo/addons/stock_warehouse_relationship/readme/DESCRIPTION.rst
odoo/addons/stock_warehouse_relationship/static/description/icon.png
odoo/addons/stock_warehouse_relationship/static/description/index.html
odoo/addons/stock_warehouse_relationship/tests/__init__.py
odoo/addons/stock_warehouse_relationship/tests/test_warehouse_relationship.py
odoo/addons/stock_warehouse_relationship/views/stock_move.xml
odoo/addons/stock_warehouse_relationship/views/stock_move_line.xml
odoo/addons/stock_warehouse_relationship/views/stock_quant.xml
odoo/addons/stock_warehouse_relationship/views/stock_quant_package.xml
odoo_addon_stock_warehouse_relationship-16.0.1.0.0.5.dist-info/METADATA
odoo_addon_stock_warehouse_relationship-16.0.1.0.0.5.dist-info/WHEEL
odoo_addon_stock_warehouse_relationship-16.0.1.0.0.5.dist-info/top_level.txt
odoo_addon_stock_warehouse_relationship-16.0.1.0.0.5.dist-info/RECORD
