Metadata-Version: 2.1
Name: odoo-addon-stock_warehouse_relationship
Version: 16.0.1.0.0.5
Summary: Technical module to add warehouse_id field on various stock.* models
Home-page: https://github.com/OCA/stock-logistics-warehouse
Author: Akretion, Pierre Verkest, Odoo Community Association (OCA)
Author-email: support@odoo-community.org
License: AGPL-3
Classifier: Programming Language :: Python
Classifier: Framework :: Odoo
Classifier: Framework :: Odoo :: 16.0
Classifier: License :: OSI Approved :: GNU Affero General Public License v3
Classifier: Development Status :: 3 - Alpha
Requires-Python: >=3.10
Requires-Dist: odoo<16.1dev,>=16.0a
